{
	"area_no": -1,
	"area_name": "全区",
	"datestamp": "2017/12/18 17:46:08",
	"content": [{
		"base_name": "GX南宁菠萝岭路口_DCSF",
		"warn_time": "2017/12/18 17:46:08",
		"area_no": "591",
		"base_lo": 108.42162410687388,
		"base_la": 22.717552347622902
	}, {
		"base_name": "GX南宁马山邓公山_GSMW",
		"warn_time": "2017/12/18 17:45:58",
		"area_no": "591",
		"base_lo": 108.31009554791417,
		"base_la": 23.64571601070112
	}, {
		"base_name": "GX南宁那马思灵江_WF",
		"warn_time": "2017/12/18 17:38:35",
		"area_no": "591",
		"base_lo": 108.49634862769236,
		"base_la": 22.551013047481767
	}, {
		"base_name": "GX桂林恭城栗木镇常家村、六岭村_U900基站_H",
		"warn_time": "2017/12/18 17:37:30",
		"area_no": "592",
		"base_lo": 111.03216436587367,
		"base_la": 25.1145293416833
	}, {
		"base_name": "GX北海合浦丰门盛世共电_FLTE1800基站_F",
		"warn_time": "2017/12/18 17:33:19",
		"area_no": "599",
		"base_lo": 109.28735645190804,
		"base_la": 21.69480594111493
	}, {
		"base_name": "GX南宁那马思灵江_GSMW",
		"warn_time": "2017/12/18 17:31:23",
		"area_no": "591",
		"base_lo": 108.5027053593812,
		"base_la": 22.53403503442541
	}, {
		"base_name": "GX梧州岑溪城西市场_GSM基站_H",
		"warn_time": "2017/12/18 17:31:18",
		"area_no": "594",
		"base_lo": 111.08572461382107,
		"base_la": 22.9705908858995
	}, {
		"base_name": "GX百色两琶_GSM基站_W",
		"warn_time": "2017/12/18 17:31:15",
		"area_no": "596",
		"base_lo": 106.56192715833296,
		"base_la": 24.181817356825796
	}, {
		"base_name": "GX梧州岑溪城西市场_FLTE基站_F",
		"warn_time": "2017/12/18 17:26:14",
		"area_no": "594",
		"base_lo": 110.1224277074379,
		"base_la": 22.940972476372007
	}, {
		"base_name": "GX桂林恭城莲花镇兰洞村_WCDMA基站_F",
		"warn_time": "2017/12/18 17:19:59",
		"area_no": "592",
		"base_lo": 111.00036389182293,
		"base_la": 24.63226044128003
	}, {
		"base_name": "GX百色两琶_WCDMA基站_F",
		"warn_time": "2017/12/18 17:19:20",
		"area_no": "596",
		"base_lo": 106.3128151588935,
		"base_la": 24.181327831173927
	}, {
		"base_name": "GX百色田林板坚_GSM基站_W",
		"warn_time": "2017/12/18 17:15:55",
		"area_no": "596",
		"base_lo": 105.88647086212384,
		"base_la": 24.718819691883585
	}, {
		"base_name": "GX桂林恭城莲花镇门等村_U900基站_H",
		"warn_time": "2017/12/18 17:10:36",
		"area_no": "592",
		"base_lo": 110.7848233273701,
		"base_la": 24.761594387339528
	}, {
		"base_name": "GX玉林北流铁山高速出口_U900基站_F",
		"warn_time": "2017/12/18 17:08:30",
		"area_no": "595",
		"base_lo": 110.12029138724476,
		"base_la": 22.853188217292505
	}, {
		"base_name": "GX玉林北流铁山高速出口_WCDMA基站_F",
		"warn_time": "2017/12/18 17:08:30",
		"area_no": "595",
		"base_lo": 110.37124916893262,
		"base_la": 22.75233241590535
	}, {
		"base_name": "GX百色田东平马太平_WCDMA基站_F",
		"warn_time": "2017/12/18 16:48:20",
		"area_no": "596",
		"base_lo": 107.20384501329305,
		"base_la": 23.527655841329473
	}, {
		"base_name": "GX梧州岑溪糯垌山顶_WCDMA基站_F",
		"warn_time": "2017/12/18 16:47:27",
		"area_no": "594",
		"base_lo": 109.85933730401558,
		"base_la": 23.03310893835399
	}, {
		"base_name": "GX桂林七星区龙隐路桂审宾馆_FLTE1800基站_F",
		"warn_time": "2017/12/18 16:47:06",
		"area_no": "592",
		"base_lo": 110.22237097879979,
		"base_la": 25.20934544039437
	}, {
		"base_name": "GX南宁吴圩西街15号_GSMF",
		"warn_time": "2017/12/18 16:46:23",
		"area_no": "591",
		"base_lo": 108.1449369281202,
		"base_la": 22.59186425100428
	}, {
		"base_name": "GX南宁新机场高速四_DCSF",
		"warn_time": "2017/12/18 16:46:23",
		"area_no": "591",
		"base_lo": 108.09666530956648,
		"base_la": 22.572905592057527
	}, {
		"base_name": "GX南宁邕宁吴圩镇二_GSMH",
		"warn_time": "2017/12/18 16:46:23",
		"area_no": "591",
		"base_lo": 108.06764478514528,
		"base_la": 22.582441650662016
	}, {
		"base_name": "GX百色德保马隘多孟_GSM基站_W",
		"warn_time": "2017/12/18 16:46:15",
		"area_no": "596",
		"base_lo": 106.69710009828209,
		"base_la": 23.343193717191333
	}, {
		"base_name": "GX南宁机场新航站楼Wfin_BBU2",
		"warn_time": "2017/12/18 16:34:03",
		"area_no": "591",
		"base_lo": 108.05513000544774,
		"base_la": 22.642361213187566
	}, {
		"base_name": "GX南宁机场新航站楼Wfin_BBU4",
		"warn_time": "2017/12/18 16:33:35",
		"area_no": "591",
		"base_lo": 108.38402578626985,
		"base_la": 22.675579029159508
	}, {
		"base_name": "GX南宁新机场高速四_WF",
		"warn_time": "2017/12/18 16:33:35",
		"area_no": "591",
		"base_lo": 108.3344089235339,
		"base_la": 22.65637315186209
	}, {
		"base_name": "GX南宁新机场新航站楼园区_WF",
		"warn_time": "2017/12/18 16:33:35",
		"area_no": "591",
		"base_lo": 108.26288136646072,
		"base_la": 22.64796231739635
	}, {
		"base_name": "GX南宁吴圩西街15号_WF",
		"warn_time": "2017/12/18 16:33:33",
		"area_no": "591",
		"base_lo": 108.31067932342522,
		"base_la": 22.71243986477037
	}, {
		"base_name": "GX南宁新机场高速三_WF",
		"warn_time": "2017/12/18 16:33:33",
		"area_no": "591",
		"base_lo": 108.30649688229342,
		"base_la": 22.560648466604317
	}, {
		"base_name": "GX南宁武鸣葛阳_GSMW",
		"warn_time": "2017/12/18 16:31:23",
		"area_no": "591",
		"base_lo": 108.55919155128365,
		"base_la": 23.00756791636543
	}, {
		"base_name": "GX贺州桂东电子厂_WCDMA基站_H",
		"warn_time": "2017/12/18 16:04:52",
		"area_no": "588",
		"base_lo": 111.72264658944057,
		"base_la": 24.457651239962846
	}, {
		"base_name": "GX百色汪甸中学_GSM基站_W",
		"warn_time": "2017/12/18 16:01:35",
		"area_no": "596",
		"base_lo": 106.22874502056304,
		"base_la": 24.220089565488173
	}, {
		"base_name": "GX来宾东盟国际_FLTE基站_H",
		"warn_time": "2017/12/18 16:01:25",
		"area_no": "601",
		"base_lo": 109.08946325045554,
		"base_la": 23.705418524612
	}, {
		"base_name": "GX来宾东盟国际_WCDMA基站1_H",
		"warn_time": "2017/12/18 15:55:58",
		"area_no": "601",
		"base_lo": 109.31662527191129,
		"base_la": 23.68788481503574
	}, {
		"base_name": "GX百色西林古障_FLTE1800基站_F",
		"warn_time": "2017/12/18 15:55:14",
		"area_no": "596",
		"base_lo": 104.55179491630233,
		"base_la": 24.549923929597206
	}, {
		"base_name": "GX百色西林古障者黑_U900基站_F",
		"warn_time": "2017/12/18 15:54:48",
		"area_no": "596",
		"base_lo": 104.72684265442304,
		"base_la": 24.54189837117323
	}, {
		"base_name": "GX崇左江州驮卢三_WCDMA基站_F",
		"warn_time": "2017/12/18 15:51:03",
		"area_no": "600",
		"base_lo": 107.42938248671649,
		"base_la": 22.60925534879266
	}, {
		"base_name": "GX崇左扶绥渠旧果米_FLTE基站_F_工程期",
		"warn_time": "2017/12/18 15:50:58",
		"area_no": "600",
		"base_lo": 107.55116124839915,
		"base_la": 22.554553144154912
	}, {
		"base_name": "GX崇左扶绥渠旧驮弄村_U900基站_F",
		"warn_time": "2017/12/18 15:50:35",
		"area_no": "600",
		"base_lo": 107.68294266472154,
		"base_la": 22.604000475966792
	}, {
		"base_name": "GX崇左扶绥渠旧_WCDMA基站_F",
		"warn_time": "2017/12/18 15:50:33",
		"area_no": "600",
		"base_lo": 108.01003964892364,
		"base_la": 22.99039200007855
	}, {
		"base_name": "GX崇左服务区_FLTE基站_F_工程期",
		"warn_time": "2017/12/18 15:50:27",
		"area_no": "600",
		"base_lo": 107.63059526801628,
		"base_la": 22.364743574468132
	}, {
		"base_name": "GX南宁凤凰塔_GSMF",
		"warn_time": "2017/12/18 15:46:22",
		"area_no": "591",
		"base_lo": 108.26344520747058,
		"base_la": 22.846572891532738
	}, {
		"base_name": "GX南宁凤凰塔_WF",
		"warn_time": "2017/12/18 15:33:03",
		"area_no": "591",
		"base_lo": 108.53618820934527,
		"base_la": 22.820837335810538
	}, {
		"base_name": "GX贵港旺华_U2100基站_H",
		"warn_time": "2017/12/18 15:22:18",
		"area_no": "589",
		"base_lo": 109.59794465212757,
		"base_la": 23.06115744285464
	}, {
		"base_name": "GX玉林福兴酒店1_WCDMA基站_F",
		"warn_time": "2017/12/18 15:20:19",
		"area_no": "595",
		"base_lo": 110.22015572536607,
		"base_la": 22.568772048991327
	}, {
		"base_name": "GX百色田阳洞靖念堂_U900基站_F",
		"warn_time": "2017/12/18 15:04:16",
		"area_no": "596",
		"base_lo": 106.28462836142045,
		"base_la": 23.626113447769683
	}, {
		"base_name": "GX柳州鹿寨波寨_WCDMA基站_H",
		"warn_time": "2017/12/18 14:48:28",
		"area_no": "593",
		"base_lo": 109.97437086024142,
		"base_la": 24.834315744696422
	}, {
		"base_name": "GX梧州岑溪糯垌山顶_GSM基站_H",
		"warn_time": "2017/12/18 14:31:18",
		"area_no": "594",
		"base_lo": 110.93976462294312,
		"base_la": 23.122243801986375
	}, {
		"base_name": "GX钦州灵山三隆镇龙山_GSM基站_H",
		"warn_time": "2017/12/18 14:16:19",
		"area_no": "597",
		"base_lo": 109.12879895675252,
		"base_la": 22.40859270850023
	}, {
		"base_name": "GX贵港桂平江口布岭_U900基站_F",
		"warn_time": "2017/12/18 13:46:13",
		"area_no": "589",
		"base_lo": 110.10818812912329,
		"base_la": 23.49621698273627
	}, {
		"base_name": "GX柳州融安红卫村村委会_FLTE基站_H",
		"warn_time": "2017/12/18 13:36:03",
		"area_no": "593",
		"base_lo": 109.5465628241542,
		"base_la": 25.15083362757958
	}, {
		"base_name": "GX河池东兰红色旅游区_WCDMA基站_F",
		"warn_time": "2017/12/18 13:22:46",
		"area_no": "598",
		"base_lo": 107.50201804624241,
		"base_la": 24.42167586982375
	}, {
		"base_name": "GX南宁启美新城_WFin(工程期)",
		"warn_time": "2017/12/18 12:45:08",
		"area_no": "591",
		"base_lo": 108.45930794805636,
		"base_la": 22.68425241364707
	}, {
		"base_name": "GX梧州藤县新庆建新_U900基站_F",
		"warn_time": "2017/12/18 12:09:32",
		"area_no": "594",
		"base_lo": 109.90842305245921,
		"base_la": 23.042798334622834
	}, {
		"base_name": "GX梧州藤县平福下双_WCDMA_F",
		"warn_time": "2017/12/18 11:26:24",
		"area_no": "594",
		"base_lo": 109.8839871683311,
		"base_la": 23.03554123307366
	}, {
		"base_name": "GX百色田阳那满新仑_GSM基站_F",
		"warn_time": "2017/12/18 10:46:15",
		"area_no": "596",
		"base_lo": 106.98826326128271,
		"base_la": 23.62717474567968
	}, {
		"base_name": "GX百色汪甸中学_WCDMA基站_F",
		"warn_time": "2017/12/18 10:45:32",
		"area_no": "596",
		"base_lo": 106.45793583742002,
		"base_la": 24.143527587901307
	}, {
		"base_name": "GX贵港五里榕木_U900基站_F",
		"warn_time": "2017/12/18 10:36:54",
		"area_no": "589",
		"base_lo": 109.56632737349632,
		"base_la": 22.963495262166305
	}, {
		"base_name": "GX贵港大岭收费站_U900基站_F",
		"warn_time": "2017/12/18 10:36:23",
		"area_no": "589",
		"base_lo": 109.40449480183165,
		"base_la": 22.85564015826878
	}, {
		"base_name": "GX贵港华润采石厂_U2100基站_H",
		"warn_time": "2017/12/18 10:36:23",
		"area_no": "589",
		"base_lo": 109.6299049287189,
		"base_la": 22.97302297840856
	}, {
		"base_name": "GX北海星海颐园_GSM1800基站_W",
		"warn_time": "2017/12/18 10:31:17",
		"area_no": "599",
		"base_lo": 109.02980421286453,
		"base_la": 21.3939317601321
	}, {
		"base_name": "GX北海山口山北_GSM基站_H",
		"warn_time": "2017/12/18 10:01:26",
		"area_no": "599",
		"base_lo": 109.66121152424634,
		"base_la": 21.684325632185203
	}, {
		"base_name": "GX南宁武鸣金都宾馆_GSMH",
		"warn_time": "2017/12/18 09:46:22",
		"area_no": "591",
		"base_lo": 108.14550049092642,
		"base_la": 23.228092622828957
	}, {
		"base_name": "GX南宁武鸣金都宾馆_WH",
		"warn_time": "2017/12/18 09:40:26",
		"area_no": "591",
		"base_lo": 108.1461901602045,
		"base_la": 23.128788841885388
	}, {
		"base_name": "GX来宾凤凰大许_FLTE基站_H",
		"warn_time": "2017/12/18 09:33:48",
		"area_no": "601",
		"base_lo": 109.44249449210953,
		"base_la": 23.894888119301353
	}, {
		"base_name": "GX来宾凤凰甘村_FLTE基站_H",
		"warn_time": "2017/12/18 09:33:48",
		"area_no": "601",
		"base_lo": 109.19070617933046,
		"base_la": 24.012934345584576
	}, {
		"base_name": "GX来宾凤凰甘村_WCDMA基站1_H",
		"warn_time": "2017/12/18 09:28:19",
		"area_no": "601",
		"base_lo": 109.4108609509751,
		"base_la": 23.92690542947363
	}, {
		"base_name": "GX百色澄碧湖新建_GSM基站_W",
		"warn_time": "2017/12/18 08:46:15",
		"area_no": "596",
		"base_lo": 106.68880884710097,
		"base_la": 23.906269165992864
	}, {
		"base_name": "GX百色澄碧湖新建_WCDMA基站_F",
		"warn_time": "2017/12/18 08:39:56",
		"area_no": "596",
		"base_lo": 106.56064568626901,
		"base_la": 23.997408186769274
	}, {
		"base_name": "GX桂林永福苏桥工业园机房一_FLTE1800基站_F",
		"warn_time": "2017/12/18 08:16:19",
		"area_no": "592",
		"base_lo": 109.86296575289037,
		"base_la": 25.18646871588078
	}, {
		"base_name": "GX百色长平电站_GSM基站_W",
		"warn_time": "2017/12/18 08:16:16",
		"area_no": "596",
		"base_lo": 106.40787624767681,
		"base_la": 24.129648847587177
	}, {
		"base_name": "GX百色长平电站_WCDMA基站_F",
		"warn_time": "2017/12/18 08:13:24",
		"area_no": "596",
		"base_lo": 106.41092169366726,
		"base_la": 24.136128017471815
	}, {
		"base_name": "GX柳州鹿寨大村林场_U900基站_H",
		"warn_time": "2017/12/18 07:04:01",
		"area_no": "593",
		"base_lo": 109.63998577501701,
		"base_la": 24.539333216704502
	}, {
		"base_name": "GX南宁东沟村二_GSMH",
		"warn_time": "2017/12/18 06:31:20",
		"area_no": "591",
		"base_lo": 108.46830052817933,
		"base_la": 22.818095933399572
	}, {
		"base_name": "GX南宁东沟岭_DCSF",
		"warn_time": "2017/12/18 06:31:20",
		"area_no": "591",
		"base_lo": 108.24636978022124,
		"base_la": 22.786779527051536
	}, {
		"base_name": "GX南宁东沟村二_WF",
		"warn_time": "2017/12/18 06:21:56",
		"area_no": "591",
		"base_lo": 108.25035749769732,
		"base_la": 22.797558266200703
	}, {
		"base_name": "GX南宁东沟岭_WF",
		"warn_time": "2017/12/18 06:21:54",
		"area_no": "591",
		"base_lo": 108.25012080265151,
		"base_la": 22.808072645649204
	}, {
		"base_name": "GX崇左扶绥芭珍_GSM基站_W",
		"warn_time": "2017/12/18 05:46:21",
		"area_no": "600",
		"base_lo": 107.44272834220257,
		"base_la": 22.82457442596565
	}, {
		"base_name": "GX贺州富川富阳大塘坝_GSM基站_W",
		"warn_time": "2017/12/18 05:01:39",
		"area_no": "588",
		"base_lo": 111.16050200910409,
		"base_la": 24.832901678460306
	}, {
		"base_name": "GX梧州藤县平福下双_GSM基站_F",
		"warn_time": "2017/12/18 04:30:58",
		"area_no": "594",
		"base_lo": 109.90417912923162,
		"base_la": 21.049309337015703
	}, {
		"base_name": "GX桂林兴安华江乡超然派景区_WCDMA基站_F",
		"warn_time": "2017/12/17 16:04:42",
		"area_no": "592",
		"base_lo": 110.41116479209798,
		"base_la": 25.80390882662872
	}, {
		"base_name": "GX来宾电厂_WCDMA基站_H",
		"warn_time": "2017/12/17 15:26:00",
		"area_no": "601",
		"base_lo": 109.29095876732788,
		"base_la": 23.64686863362651
	}, {
		"base_name": "GX百色城东收费站_WCDMA基站_F",
		"warn_time": "2017/12/17 15:04:12",
		"area_no": "596",
		"base_lo": 106.61418220493607,
		"base_la": 23.782520384087448
	}, {
		"base_name": "GX崇左扶绥芭珍_WCDMA基站_F",
		"warn_time": "2017/12/17 14:42:44",
		"area_no": "600",
		"base_lo": 107.05536641155496,
		"base_la": 35.34931238356358
	}, {
		"base_name": "GX百色城东收费站_GSM基站_W",
		"warn_time": "2017/12/17 14:01:35",
		"area_no": "596",
		"base_lo": 106.58159513713787,
		"base_la": 23.757146112416258
	}, {
		"base_name": "GX南宁环城二塘互通_WF",
		"warn_time": "2017/12/17 09:40:39",
		"area_no": "591",
		"base_lo": 108.45407464768294,
		"base_la": 22.928345867603728
	}, {
		"base_name": "GX桂林灵川灵田乡东田村_FLTE1800基站_F",
		"warn_time": "2017/12/17 09:31:45",
		"area_no": "592",
		"base_lo": 110.1552305766697,
		"base_la": 25.284006741576793
	}, {
		"base_name": "GX南宁三岸_DCSW",
		"warn_time": "2017/12/17 08:01:49",
		"area_no": "591",
		"base_lo": 108.34093800390357,
		"base_la": 22.837387279813647
	}, {
		"base_name": "GX桂林兴安秦皇路尾_WCDMA基站_F",
		"warn_time": "2017/12/17 03:42:19",
		"area_no": "592",
		"base_lo": 110.60522134823889,
		"base_la": 25.65380655129049
	}, {
		"base_name": "GX南宁武鸣城厢良一_GSMF",
		"warn_time": "2017/12/16 22:31:22",
		"area_no": "591",
		"base_lo": 108.45346492532657,
		"base_la": 23.122921606985745
	}, {
		"base_name": "GX南宁武鸣正安农场_GSMW",
		"warn_time": "2017/12/16 22:01:49",
		"area_no": "591",
		"base_lo": 107.9831767090958,
		"base_la": 23.223364722484114
	}, {
		"base_name": "GX南宁隆安新兴二_GSMF",
		"warn_time": "2017/12/16 19:01:51",
		"area_no": "591",
		"base_lo": 107.64601005224883,
		"base_la": 23.202062962140545
	}, {
		"base_name": "GX南宁隆安新兴二_U900基站_F",
		"warn_time": "2017/12/16 18:49:04",
		"area_no": "591",
		"base_lo": 107.88661683744706,
		"base_la": 23.08697409109491
	}, {
		"base_name": "GX南宁隆安新兴二_WF",
		"warn_time": "2017/12/16 18:49:03",
		"area_no": "591",
		"base_lo": 107.84979884076868,
		"base_la": 23.098430003978564
	}, {
		"base_name": "GX南宁宾阳黎塘老桥美_GSMW",
		"warn_time": "2017/12/16 18:16:21",
		"area_no": "591",
		"base_lo": 108.76278487289981,
		"base_la": 23.29807937607177
	}, {
		"base_name": "GX北海合浦常乐农行_GSM基站_H",
		"warn_time": "2017/12/16 06:01:15",
		"area_no": "599",
		"base_lo": 109.34404257686764,
		"base_la": 21.863650872943463
	}, {
		"base_name": "GX南宁武鸣大皇后木材厂_GSMF",
		"warn_time": "2017/12/15 14:31:23",
		"area_no": "591",
		"base_lo": 108.31613694988091,
		"base_la": 23.17718092803697
	}, {
		"base_name": "GX柳州柳北青茅村_FLTE基站_H",
		"warn_time": "2017/12/14 20:00:20",
		"area_no": "593",
		"base_lo": 109.53630065860797,
		"base_la": 24.375089438162185
	}, {
		"base_name": "GX桂林全州才湾镇白石村_WCDMA基站_F",
		"warn_time": "2017/12/14 18:16:16",
		"area_no": "592",
		"base_lo": 110.18299370223822,
		"base_la": 25.145508012153186
	}, {
		"base_name": "GX桂林全州才湾镇田心村_WCDMA基站_F",
		"warn_time": "2017/12/14 18:16:16",
		"area_no": "592",
		"base_lo": 110.65085026524528,
		"base_la": 25.36851282110742
	}, {
		"base_name": "GX桂林全州才湾镇下坊村_U900基站_H",
		"warn_time": "2017/12/14 18:05:50",
		"area_no": "592",
		"base_lo": 110.86077408125392,
		"base_la": 25.906885416480986
	}, {
		"base_name": "GX桂林象山区东风被服厂_WCDMA基站_F",
		"warn_time": "2017/12/14 15:41:20",
		"area_no": "592",
		"base_lo": 110.14892029013198,
		"base_la": 25.195227844563163
	}, {
		"base_name": "GX桂林东风被服厂_FLTE1800基站_F",
		"warn_time": "2017/12/14 15:34:52",
		"area_no": "592",
		"base_lo": 110.52728025846193,
		"base_la": 25.115871582886914
	}, {
		"base_name": "GX南宁振宁大厦_DCSF",
		"warn_time": "2017/12/14 08:16:07",
		"area_no": "591",
		"base_lo": 108.36253299152979,
		"base_la": 22.87615524123599
	}, {
		"base_name": "GX南宁良庆区五象商业街项目部_DCSF(备)",
		"warn_time": "2017/12/13 23:31:24",
		"area_no": "591",
		"base_lo": 108.43470383667531,
		"base_la": 22.70150211209225
	}, {
		"base_name": "GX玉林福绵樟木胜利_U900基站_F",
		"warn_time": "2017/12/13 21:50:01",
		"area_no": "595",
		"base_lo": 110.19643404651035,
		"base_la": 22.570285616362725
	}, {
		"base_name": "GX河池大化镇西_U900基站_F",
		"warn_time": "2017/12/12 14:07:20",
		"area_no": "598",
		"base_lo": 107.87725254013023,
		"base_la": 23.969509287199315
	}, {
		"base_name": "GX梧州蒙山妇幼医院_GSM基站_H",
		"warn_time": "2017/12/11 20:30:56",
		"area_no": "594",
		"base_lo": 110.39415010068726,
		"base_la": 24.17343566034263
	}, {
		"base_name": "GX百色靖西壮锦大酒店_FLTE1800基站_F",
		"warn_time": "2017/12/11 18:51:22",
		"area_no": "596",
		"base_lo": 106.28888167298267,
		"base_la": 23.200845178886983
	}, {
		"base_name": "GX百色靖西壮锦大酒店_WCDMA基站_F",
		"warn_time": "2017/12/11 18:51:04",
		"area_no": "596",
		"base_lo": 106.28270126728889,
		"base_la": 23.180277404855843
	}, {
		"base_name": "GX桂林东安北街二巷_WCDMA基站_F",
		"warn_time": "2017/12/11 14:13:08",
		"area_no": "592",
		"base_lo": 110.41692811133196,
		"base_la": 25.308455081838694
	}, {
		"base_name": "GX南宁武鸣高速收费站二_WF",
		"warn_time": "2017/12/11 12:07:35",
		"area_no": "591",
		"base_lo": 108.17142981035313,
		"base_la": 23.115285361342583
	}, {
		"base_name": "GX桂林灵川八里街八里六路_WCDMA基站_F",
		"warn_time": "2017/12/10 16:02:42",
		"area_no": "592",
		"base_lo": 110.37998455414166,
		"base_la": 25.40460564837566
	}, {
		"base_name": "GX南宁九塘管乙_WF",
		"warn_time": "2017/12/09 15:09:51",
		"area_no": "591",
		"base_lo": 108.5688502487049,
		"base_la": 22.943302303984684
	}, {
		"base_name": "GX桂林全州永岁乡_WCDMA基站_F",
		"warn_time": "2017/12/04 09:05:44",
		"area_no": "592",
		"base_lo": 111.00443097290106,
		"base_la": 26.073152672853162
	}, {
		"base_name": "GX桂林全州永岁乡新塘坪村_WCDMA基站_F",
		"warn_time": "2017/12/04 09:05:03",
		"area_no": "592",
		"base_lo": 110.44184968042381,
		"base_la": 25.308821589533817
	}, {
		"base_name": "GX桂林全州永岁乡新塘坪村_WCDMA基站_F",
		"warn_time": "2017/12/04 09:05:03",
		"area_no": "592",
		"base_lo": 111.2025058561646,
		"base_la": 25.934853870268732
	}, {
		"base_name": "GX桂林全州黄沙河镇前进街_WCDMA基站_F",
		"warn_time": "2017/12/04 09:04:33",
		"area_no": "592",
		"base_lo": 111.0559714545569,
		"base_la": 26.02682927174266
	}, {
		"base_name": "GX桂林全州永岁乡港底村_WCDMA基站_F",
		"warn_time": "2017/12/04 09:04:32",
		"area_no": "592",
		"base_lo": 111.07185454558758,
		"base_la": 26.000760490465233
	}, {
		"base_name": "GX桂林全州黄沙河镇_WCDMA基站_Fin",
		"warn_time": "2017/12/04 09:04:31",
		"area_no": "592",
		"base_lo": 111.1007527049007,
		"base_la": 26.03540849415636
	}, {
		"base_name": "GX桂林全州黄沙河镇市场_WCDMA基站_F",
		"warn_time": "2017/12/04 09:04:31",
		"area_no": "592",
		"base_lo": 111.14999400660858,
		"base_la": 26.14176612606142
	}, {
		"base_name": "GX桂林全州永岁乡_WCDMA基站_Fin",
		"warn_time": "2017/12/04 09:03:51",
		"area_no": "592",
		"base_lo": 110.39250417257641,
		"base_la": 26.061446395042392
	}, {
		"base_name": "GX钦州灵山陆屋镇糖厂_GSM基站_H",
		"warn_time": "2017/12/04 00:31:18",
		"area_no": "597",
		"base_lo": 109.0451142181914,
		"base_la": 22.24193135189004
	}, {
		"base_name": "GX河池都安大兴九香新村_WCDMA基站_F",
		"warn_time": "2017/12/03 18:15:50",
		"area_no": "598",
		"base_lo": 108.06330909296311,
		"base_la": 24.184842923953262
	}, {
		"base_name": "GX百色真龙大酒店_GSM1800基站_F",
		"warn_time": "2017/12/01 08:01:35",
		"area_no": "596",
		"base_lo": 106.48771396591923,
		"base_la": 23.940028099015148
	}],
	"centent_size": 124,
	"center_lo": 108.0861245,
	"center_la": 28.1547,
	"city_all": [{
		"area_name": "百色",
		"warn_all": 20
	}, {
		"area_name": "北海",
		"warn_all": 4
	}, {
		"area_name": "崇左",
		"warn_all": 7
	}, {
		"area_name": "防城港",
		"warn_all": 0
	}, {
		"area_name": "桂林",
		"warn_all": 22
	}, {
		"area_name": "贵港",
		"warn_all": 5
	}, {
		"area_name": "河池",
		"warn_all": 3
	}, {
		"area_name": "贺州",
		"warn_all": 2
	}, {
		"area_name": "来宾",
		"warn_all": 6
	}, {
		"area_name": "柳州",
		"warn_all": 4
	}, {
		"area_name": "南宁",
		"warn_all": 36
	}, {
		"area_name": "钦州",
		"warn_all": 2
	}, {
		"area_name": "梧州",
		"warn_all": 8
	}, {
		"area_name": "玉林",
		"warn_all": 4
	}]
}